MANIFEST.in
README.rst
setup.cfg
setup.py
docs/HISTORY.txt
docs/INSTALL.txt
docs/LICENSE.GPL
docs/LICENSE.txt
medialog/.DS_Store
medialog/__init__.py
medialog/__init__.pyc
medialog.markdown.egg-info/PKG-INFO
medialog.markdown.egg-info/SOURCES.txt
medialog.markdown.egg-info/dependency_links.txt
medialog.markdown.egg-info/entry_points.txt
medialog.markdown.egg-info/namespace_packages.txt
medialog.markdown.egg-info/not-zip-safe
medialog.markdown.egg-info/requires.txt
medialog.markdown.egg-info/top_level.txt
medialog/markdown/.DS_Store
medialog/markdown/__init__.py
medialog/markdown/__init__.pyc
medialog/markdown/behavior.py
medialog/markdown/behavior.pyc
medialog/markdown/behaviors.zcml
medialog/markdown/configure.zcml
medialog/markdown/interfaces.py
medialog/markdown/interfaces.pyc
medialog/markdown/tests.py
medialog/markdown/browser/__init__.py
medialog/markdown/browser/__init__.pyc
medialog/markdown/browser/configure.zcml
medialog/markdown/browser/markdowntile.pt
medialog/markdown/browser/views.py
medialog/markdown/browser/views.pyc
medialog/markdown/locales/README.txt
medialog/markdown/profiles/default/metadata.xml
medialog/markdown/profiles/default/registry.xml
medialog/markdown/resources/ace-extra.min.js
medialog/markdown/resources/bootstrap-markdown.min.js
medialog/markdown/resources/bootstrap-markdown.nb.js
medialog/markdown/resources/jquery.selection.js
medialog/markdown/resources/markdown.css
medialog/markdown/resources/markdown.min.js
medialog/markdown/resources/modxMagicHoverLink.js
medialog/markdown/resources/tinymceBubbleBar.js
medialog/markdown/resources/twExoticMarkdownEditor.js
medialog/markdown/resources/twPreCodeManager.js
medialog/markdown/templates/render_markdown.pt
medialog/markdown/tiles/__init__.py
medialog/markdown/tiles/__init__.pyc
medialog/markdown/tiles/configure.zcml
medialog/markdown/tiles/markdowntile.pt
medialog/markdown/tiles/tile.py
medialog/markdown/tiles/tile.pyc
medialog/markdown/widgets/__init__.py
medialog/markdown/widgets/__init__.pyc
medialog/markdown/widgets/configure.zcml
medialog/markdown/widgets/markdown_display.pt
medialog/markdown/widgets/markdown_input.pt
medialog/markdown/widgets/widget.py
medialog/markdown/widgets/widget.pyc