Metadata-Version: 1.1
Name: medialog.markdown
Version: 0.2.1
Summary: markdown for Plone
Home-page: http://github.com/espenmn/medialog.markdown
Author: Espen Moe-Nilssen
Author-email: espen@medialog.no
License: GPL
Platform: UNKNOWN
Classifier: Framework :: Plone
Classifier: Programming Language :: Python
Classifier: Topic :: Software Development :: Libraries :: Python Modules
